logicmin/__init__.py
logicmin/assign.py
logicmin/binary.py
logicmin/cube.py
logicmin/expr2l.py
logicmin/expr2vhdl.py
logicmin/fsm.py
logicmin/logic.py
logicmin/minterm.py
logicmin/multisol.py
logicmin/numsys.py
logicmin/sol.py
logicmin/sop.py
logicmin/tt.py
logicmin-0.4.0.dist-info/LICENSE.txt
logicmin-0.4.0.dist-info/METADATA
logicmin-0.4.0.dist-info/WHEEL
logicmin-0.4.0.dist-info/top_level.txt
logicmin-0.4.0.dist-info/RECORD
