Metadata-Version: 2.1
Name: logicmin
Version: 0.4.0
Summary: Logic Minimization
Home-page: http://github.com/dreylago/logicmin
Author: Demetrio Rey
Author-email: demetrio.rey@gmail.com
License: MIT
Classifier: Development Status :: 3 - Alpha
Classifier: License :: OSI Approved :: MIT License
Classifier: Programming Language :: Python :: 2
Classifier: Programming Language :: Python :: 2.7
Classifier: Programming Language :: Python :: 3
Classifier: Programming Language :: Python :: 3.6
Classifier: Intended Audience :: End Users/Desktop
Classifier: Topic :: Scientific/Engineering :: Electronic Design Automation (EDA)
Requires-Python: >=2.7
License-File: LICENSE.txt
Requires-Dist: future
